impkinpy/__init__.py
impkinpy/astro/__init__.py
impkinpy/astro/ast_time.py
impkinpy/astro/space.py
impkinpy/mechanics/__init__.py
impkinpy/mechanics/gravity.py
impkinpy/mechanics/impulse_energy.py
impkinpy-1.0.7.dist-info/licenses/LICENSE.md
impkinpy-1.0.7.dist-info/METADATA
impkinpy-1.0.7.dist-info/WHEEL
impkinpy-1.0.7.dist-info/top_level.txt
impkinpy-1.0.7.dist-info/RECORD
