Metadata-Version: 2.4
Name: impkinpy
Version: 1.0.7
Summary: Library for mechanics and astronomy
Home-page: https://github.com/Viktor640266/impkinpy
Author: Vitek
Author-email: Vitek <cheeseqwertycheese@gmail.com>
License: MIT
Requires-Python: >=3.7
License-File: LICENSE.md
Requires-Dist: numpy
Requires-Dist: scipy
Requires-Dist: matplotlib
Dynamic: author
Dynamic: home-page
Dynamic: license-file
Dynamic: requires-python
